typeformtools/__init__.py
typeformtools/py.typed
typeformtools-0.1.14.dist-info/METADATA
typeformtools-0.1.14.dist-info/WHEEL
typeformtools-0.1.14.dist-info/RECORD
