Metadata-Version: 2.4
Name: typeformtools
Version: 0.1.14
Summary: TypeForm helpers
Author: Olaf
License: MIT License
Classifier: Development Status :: 2 - Pre-Alpha
Classifier: Intended Audience :: Developers
Classifier: License :: OSI Approved :: MIT License
Classifier: Programming Language :: Python :: 3.12
Classifier: Programming Language :: Python :: 3.13
Classifier: Programming Language :: Python :: 3.14
Classifier: Typing :: Typed
Requires-Python: >=3.12
Requires-Dist: annotated-types
Requires-Dist: more-itertools
Requires-Dist: typing-extensions>=4.13
Requires-Dist: useful-types
